gptscript/__init__.py
gptscript/confirm.py
gptscript/credentials.py
gptscript/daemon.py
gptscript/datasets.py
gptscript/exec_utils.py
gptscript/fileinfo.py
gptscript/frame.py
gptscript/gptscript.py
gptscript/install.py
gptscript/openai.py
gptscript/opts.py
gptscript/prompt.py
gptscript/run.py
gptscript/text.py
gptscript/tool.py
gptscript-0.9.8.dist-info/licenses/LICENSE
gptscript-0.9.8.dist-info/METADATA
gptscript-0.9.8.dist-info/WHEEL
gptscript-0.9.8.dist-info/entry_points.txt
gptscript-0.9.8.dist-info/top_level.txt
gptscript-0.9.8.dist-info/RECORD
