Metadata-Version: 2.4
Name: gptscript
Version: 0.9.8
Summary: Run gptscripts from Python apps
Author-email: Bill Maxwell <bill@acorn.io>
License: 
Project-URL: Homepage, https://github.com/gptscript-ai/py-gptscript/
Project-URL: Issues, https://github.com/gptscript-ai/py-gptscript/issues
Project-URL: Repository, https://github.com/gptscript-ai/py-gptscript.git
License-File: LICENSE
Requires-Dist: certifi==2024.7.4
Requires-Dist: charset-normalizer==3.3.2
Requires-Dist: httpx==0.27.0
Requires-Dist: idna==3.7
Requires-Dist: requests==2.32.2
Requires-Dist: tqdm==4.66.3
Requires-Dist: urllib3==2.6.2
Requires-Dist: pydantic==2.12.5
Requires-Dist: pywin32==311; sys_platform == "win32"
Requires-Dist: uvicorn==0.38.0
Dynamic: license-file
